{
    "name": "athena",
    "dependencies": {
        "core": "*",
        "radio": "*",
        "pxt-sonar": "github:microsoft/pxt-sonar#v0.0.5",
        "motor": "github:dfrobot/pxt-motor#dbd0aa1f999cc925785006df8ee6581307ec3140",
        "neopixel": "github:microsoft/pxt-neopixel#v0.6.12",
        "pxt-esp8266_thingspeak": "github:alankrantas/pxt-esp8266_thingspeak#v0.0.3",
        "pxt-DHT11_DHT22": "github:alankrantas/pxt-dht11_dht22#v0.0.1"
    },
    "description": "",
    "files": [
        "main.ts",
        "README.md",
        "custom.ts"
    ],
    "preferredEditor": "tsprj"
}